demos/__init__.py
demos/books_service.py
demos/create_customer.py
demos/customer_service.py
demos/delete_customer.py
demos/echo_service.py
demos/echo_service_sugar_stx.py
demos/person_service.py
demos/serv-1.py
demos/serv-2.py
demos/update_customer.py
pyrestful/__init__.py
pyrestful/converttype.py
pyrestful/mediatypes.py
pyrestful/rest.py
pyrestful/types.py
test/README.py
test/__init__.py
test/serv-1.py
test/serv-2.py
test/tests.py
test/tests_sugar_sintax.py
test/tests_sugar_syntax.py
pyrestful-0.5.1.dist-info/METADATA
pyrestful-0.5.1.dist-info/WHEEL
pyrestful-0.5.1.dist-info/top_level.txt
pyrestful-0.5.1.dist-info/RECORD
